[
    {
        "category": "arts_and_literature",
        "id": "622a1c397cc59eab6f950f41",
        "correctAnswer": "Carbon Dioxide",
        "incorrectAnswers": [
            "Oxygen",
            "Nitrogen",
            "Hydrogen"
        ],
        "question": {
            "text": "What is the primary greenhouse gas responsible for climate change?"
        },
        "tags": [
            "arts_and_literature"
        ],
        "type": "text_choice",
        "difficulty": "hard",
        "regions": [],
        "isNiche": false
    },
    {
        "category": "arts_and_literature",
        "id": "622a1c397cc59eab6f950f3d",
        "correctAnswer": "Rising Sea Levels",
        "incorrectAnswers": [
            "Increased Biodiversity",
            "Decreased Global Temperatures",
            "More stable weather patterns"
        ],
        "question": {
            "text": "Which of the follwing is a consequence of climate change?"
        },
        "tags": [
            "literature",
            "fantasy",
            "arts_and_literature"
        ],
        "type": "text_choice",
        "difficulty": "medium",
        "regions": [],
        "isNiche": false
    },
    {
        "category": "arts_and_literature",
        "id": "622a1c347cc59eab6f94fa32",
        "correctAnswer": "Human Activities- Open Burning",
        "incorrectAnswers": [
            "Solar Flares",
            "Ocean Currents",
            "Natural Volcanic Activity"
        ],
        "question": {
            "text": "What is the main cause of the enhanced greenhouse effect?"
        },
        "tags": [
            "art",
            "painting",
            "arts_and_literature"
        ],
        "type": "text_choice",
        "difficulty": "hard",
        "regions": [],
        "isNiche": false
    },
    {
        "category": "arts_and_literature",
        "id": "622a1c397cc59eab6f950f9a",
        "correctAnswer": "Paris Agreement",
        "incorrectAnswers": [
            "Kyoto Protocol",
            "Monotreal Protocol",
            "Geneva Convention"
        ],
        "question": {
            "text": "Which international agreement aims to limit global warming to below 2°C above pre-industrial levels?"
        },
        "tags": [
            "arts_and_literature"
        ],
        "type": "text_choice",
        "difficulty": "easy",
        "regions": [],
        "isNiche": false
    },
    {
        "category": "arts_and_literature",
        "id": "622a1c3a7cc59eab6f9512f6",
        "correctAnswer": "By reducing carbon dioxide absorption",
        "incorrectAnswers": [
            "By incresing oxygen levels",
            "By cooling the Earth's surface",
            "By increasing rainfall"
        ],
        "question": {
            "text": "How does deforestation contribute to climate change"
        },
        "tags": [
            "arts_and_literature",
            "literature",
            "people"
        ],
        "type": "text_choice",
        "difficulty": "medium",
        "regions": [],
        "isNiche": false
    },
    {
        "category": "arts_and_literature",
        "id": "622a1c3c7cc59eab6f951896",
        "correctAnswer": "Energy Production",
        "incorrectAnswers": [
            "Agriculture",
            "Transportation",
            "Industry"
        ],
        "question": {
            "text": "Which sector is the largest contributor to global greenhouse gas emissions?"
        },
        "tags": [
            "literature",
            "people",
            "pseudonyms",
            "arts_and_literature"
        ],
        "type": "text_choice",
        "difficulty": "hard",
        "regions": [],
        "isNiche": false
    },
    {
        "category": "arts_and_literature",
        "id": "622a1c3b7cc59eab6f9513d1",
        "correctAnswer": "Sea levels increase",
        "incorrectAnswers": [
            "Sea Level Decrease",
            "Sea levels remain the same",
            "Sea levels fluctuate"
        ],
        "question": {
            "text": "What is the effect of melting polar ice caps on sea levels?"
        },
        "tags": [
            "literature",
            "fictitious_characters",
            "young_adult",
            "arts_and_literature"
        ],
        "type": "text_choice",
        "difficulty": "easy",
        "regions": [],
        "isNiche": false
    },
    {
        "category": "arts_and_literature",
        "id": "622a1c3a7cc59eab6f951394",
        "correctAnswer": "Solar Power",
        "incorrectAnswers": [
            "Coal",
            "Natural Gas",
            "Nuclear Power"
        ],
        "question": {
            "text": "Which of the follwing is a renewable enrgy source that can help reduce climate change?"
        },
        "tags": [
            "arts_and_literature"
        ],
        "type": "text_choice",
        "difficulty": "medium",
        "regions": [],
        "isNiche": false
    },
    {
        "category": "arts_and_literature",
        "id": "622a1c347cc59eab6f94fa1d",
        "correctAnswer": "Dubai",
        "incorrectAnswers": [
            "Malaysia",
            "USA",
            "China"
        ],
        "question": {
            "text": "Where does 28th United Nations Climate Change annual conference held?"
        },
        "tags": [
            "art",
            "painting",
            "arts_and_literature"
        ],
        "type": "text_choice",
        "difficulty": "medium",
        "regions": [],
        "isNiche": false
    },
    {
        "category": "arts_and_literature",
        "id": "622a1c347cc59eab6f94f95f",
        "correctAnswer": "Reduce, Reuse, Recycle",
        "incorrectAnswers": [
            "Use more plastic products",
            "Drive more frequently",
            "Increase Energy Consumption"
        ],
        "question": {
            "text": "Which of the following actions can individuals take to help combat climate change?"
        },
        "tags": [
            "literature",
            "fictitious_characters",
            "arts_and_literature"
        ],
        "type": "text_choice",
        "difficulty": "hard",
        "regions": [],
        "isNiche": false
    }
]
